{
	"你好": [
		[
			{
				"type": "text",
				"text": "你好",
				"from_user": {
					"card": "纸巾akura",
					"nickname": "Akura",
					"user_id": 2902458976
				}
			}
		]
	],
	"男娘": [
		[
			{
				"type": "text",
				"text": "你是",
				"from_user": {
					"card": "纸巾akura",
					"nickname": "Akura",
					"user_id": 2902458976
				}
			}
		]
	],
	"你是": [
		[
			{
				"type": "text",
				"text": "男娘",
				"from_user": {
					"card": "纸巾akura",
					"nickname": "Akura",
					"user_id": 2902458976
				}
			}
		]
	]
}