{
	"副作用": [
		[
			{
				"type": "text",
				"text": "身上的钱被赤色杀人魔全部抢走",
				"from_user": {
					"card": "［］小号转生大号版",
					"nickname": "迷の懵懂",
					"user_id": 1467616431
				}
			}
		],
		[
			{
				"type": "text",
				"text": "自己变成并小南娘随机传送到群u床上",
				"from_user": {
					"card": "呜呜污污污",
					"nickname": "鸮",
					"user_id": 1216637577
				}
			}
		]
	],
	"超能力": [
		[
			{
				"type": "text",
				"text": "往所有群友的手机里下载110g的zzz",
				"from_user": {
					"card": "［］小号转生大号版",
					"nickname": "迷の懵懂",
					"user_id": 1467616431
				}
			}
		]
	]
}